pydantic_encryption/__init__.py
pydantic_encryption/_lazy.py
pydantic_encryption/adapters/__init__.py
pydantic_encryption/adapters/base.py
pydantic_encryption/adapters/encryption/__init__.py
pydantic_encryption/adapters/encryption/aws.py
pydantic_encryption/adapters/encryption/evervault.py
pydantic_encryption/adapters/encryption/fernet.py
pydantic_encryption/adapters/hashing/__init__.py
pydantic_encryption/adapters/hashing/argon2.py
pydantic_encryption/config.py
pydantic_encryption/integrations/__init__.py
pydantic_encryption/integrations/sqlalchemy.py
pydantic_encryption/models/__init__.py
pydantic_encryption/models/base.py
pydantic_encryption/types.py
pydantic_encryption-0.3.1.dist-info/METADATA
pydantic_encryption-0.3.1.dist-info/WHEEL
pydantic_encryption-0.3.1.dist-info/entry_points.txt
pydantic_encryption-0.3.1.dist-info/licenses/LICENSE
pydantic_encryption-0.3.1.dist-info/RECORD
