Metadata-Version: 2.4
Name: pydantic_encryption
Version: 0.3.1
Summary: Encryption and Hashing Models for Pydantic
License-File: LICENSE
Author: Julien Kmec
Author-email: me@julien.dev
Requires-Python: >=3.11,<3.15
Classifier: Programming Language :: Python :: 3
Classifier: Programming Language :: Python :: 3.11
Classifier: Programming Language :: Python :: 3.12
Classifier: Programming Language :: Python :: 3.13
Classifier: Programming Language :: Python :: 3.14
Provides-Extra: all
Provides-Extra: aws
Provides-Extra: dev
Provides-Extra: evervault
Provides-Extra: sqlalchemy
Requires-Dist: argon2-cffi (>=23.1.0)
Requires-Dist: aws-encryption-sdk[mpl] (>=4.0.1) ; extra == "all"
Requires-Dist: aws-encryption-sdk[mpl] (>=4.0.1) ; extra == "aws"
Requires-Dist: boto3 (>=1.38.8) ; extra == "all"
Requires-Dist: boto3 (>=1.38.8) ; extra == "aws"
Requires-Dist: coverage (>=7.8.0) ; extra == "dev"
Requires-Dist: cryptography (>=44.0.0)
Requires-Dist: evervault (>=4.4.1) ; extra == "all"
Requires-Dist: evervault (>=4.4.1) ; extra == "evervault"
Requires-Dist: polyfactory (>=2.0.0) ; extra == "dev"
Requires-Dist: psycopg2-binary (>=2.9.10) ; extra == "dev"
Requires-Dist: pydantic (>=2.10.6)
Requires-Dist: pydantic-settings (>=2.9.1)
Requires-Dist: pydantic-super-model (>=1.1.2)
Requires-Dist: pytest (>=8.3.5) ; extra == "dev"
Requires-Dist: pytest-asyncio (>=0.26.0) ; extra == "dev"
Requires-Dist: pytest-cov (>=6.1.1) ; extra == "dev"
Requires-Dist: pytest-docker (>=3.2.1) ; extra == "dev"
Requires-Dist: pytest-env (>=1.1.5) ; extra == "dev"
Requires-Dist: pytest-sqlalchemy (>=0.3.0) ; extra == "dev"
Requires-Dist: sqlalchemy (>=2.0.40) ; extra == "all"
Requires-Dist: sqlalchemy (>=2.0.40) ; extra == "sqlalchemy"
Requires-Dist: sqlalchemy-utils (>=0.41.2) ; extra == "dev"
Requires-Dist: sqlmodel (>=0.0.24) ; extra == "all"
Requires-Dist: sqlmodel (>=0.0.24) ; extra == "sqlalchemy"
Project-URL: Repository, https://github.com/julien777z/pydantic-encryption
